hyperon_das_atomdb/__init__.py
hyperon_das_atomdb/adapters/__init__.py
hyperon_das_atomdb/adapters/ram_only.py
hyperon_das_atomdb/adapters/redis_mongo_db.py
hyperon_das_atomdb/adapters/server_db.py
hyperon_das_atomdb/constants/__init__.py
hyperon_das_atomdb/constants/redis_mongo_db.py
hyperon_das_atomdb/entity.py
hyperon_das_atomdb/exceptions.py
hyperon_das_atomdb/i_database.py
hyperon_das_atomdb/logger.py
hyperon_das_atomdb/utils/__init__.py
hyperon_das_atomdb/utils/decorators.py
hyperon_das_atomdb/utils/expression_hasher.py
hyperon_das_atomdb/utils/patterns.py
hyperon_das_atomdb/utils/settings.py
capozzoli_testando_hyperon_das_atomdb-0.1.0.dist-info/METADATA
capozzoli_testando_hyperon_das_atomdb-0.1.0.dist-info/WHEEL
capozzoli_testando_hyperon_das_atomdb-0.1.0.dist-info/RECORD
