Metadata-Version: 2.1
Name: capozzoli-testando-hyperon-das-atomdb
Version: 0.1.0
Summary: Persistence layer for Distributed AtomSpace
Author: marcocapozzoli
Author-email: marcocapozzoli90@gmail.com
Requires-Python: >=3.8.5,<4.0.0
Classifier: Programming Language :: Python :: 3
Classifier: Programming Language :: Python :: 3.9
Classifier: Programming Language :: Python :: 3.10
Classifier: Programming Language :: Python :: 3.11
Requires-Dist: pymongo (>=4.5.0,<5.0.0)
Requires-Dist: python-dotenv (>=1.0.0,<2.0.0)
Requires-Dist: redis (>=5.0.0,<6.0.0)
Requires-Dist: requests (>=2.31.0,<3.0.0)
Requires-Dist: requests-mock (>=1.11.0,<2.0.0)
